masci_tools/__init__.py
masci_tools/py.typed
masci_tools/cmdline/__init__.py
masci_tools/cmdline/commands/__init__.py
masci_tools/cmdline/commands/convert_inpgen.py
masci_tools/cmdline/commands/fleur_schema.py
masci_tools/cmdline/commands/parse.py
masci_tools/cmdline/commands/plot.py
masci_tools/cmdline/commands/root.py
masci_tools/cmdline/commands/tools.py
masci_tools/cmdline/parameters/__init__.py
masci_tools/cmdline/parameters/slice.py
masci_tools/cmdline/utils/__init__.py
masci_tools/cmdline/utils/echo.py
masci_tools/io/__init__.py
masci_tools/io/cif2inp_ase.py
masci_tools/io/common_functions.py
masci_tools/io/fleur_inpgen.py
masci_tools/io/fleur_xml.py
masci_tools/io/fleurxmlmodifier.py
masci_tools/io/hdf5_util.py
masci_tools/io/io_fleurxml.py
masci_tools/io/io_nmmpmat.py
masci_tools/io/kkr_params.py
masci_tools/io/kkr_read_shapefun_info.py
masci_tools/io/modify_potential.py
masci_tools/io/parsers/__init__.py
masci_tools/io/parsers/kkrimp_parser_functions.py
masci_tools/io/parsers/kkrparser_functions.py
masci_tools/io/parsers/voroparser_functions.py
masci_tools/io/parsers/fleur/__init__.py
masci_tools/io/parsers/fleur/default_parse_tasks.py
masci_tools/io/parsers/fleur/fleur_inpxml_parser.py
masci_tools/io/parsers/fleur/fleur_outxml_parser.py
masci_tools/io/parsers/fleur/outxml_conversions.py
masci_tools/io/parsers/fleur/task_migrations.py
masci_tools/io/parsers/fleur/fleur_schema/__init__.py
masci_tools/io/parsers/fleur_schema/__init__.py
masci_tools/io/parsers/fleur_schema/fleur_schema_parser_functions.py
masci_tools/io/parsers/fleur_schema/inpschema_todict.py
masci_tools/io/parsers/fleur_schema/outschema_todict.py
masci_tools/io/parsers/fleur_schema/schema_dict.py
masci_tools/io/parsers/fleur_schema/0.27/FleurInputSchema.xsd
masci_tools/io/parsers/fleur_schema/0.28/FleurInputSchema.xsd
masci_tools/io/parsers/fleur_schema/0.29/FleurInputSchema.xsd
masci_tools/io/parsers/fleur_schema/0.29/FleurOutputSchema.xsd
masci_tools-0.15.0.dist-info/entry_points.txt
masci_tools-0.15.0.dist-info/LICENSE.txt
masci_tools-0.15.0.dist-info/WHEEL
masci_tools-0.15.0.dist-info/METADATA
masci_tools-0.15.0.dist-info/RECORD
