Metadata-Version: 2.1
Name: masci-tools
Version: 0.15.0
Summary: masci-tools is a collection of tools for materials science.
Keywords: material science,plots,fitting,visualization,aiida,dft,all-electron
Author-email: The JuDFT team <j.broeder@fz-juelich.de>
Requires-Python: >=3.7
Classifier: Development Status :: 4 - Beta
Classifier: Intended Audience :: Science/Research
Classifier: License :: OSI Approved :: MIT License
Classifier: Programming Language :: Python :: 3
Classifier: Programming Language :: Python :: 3.7
Classifier: Programming Language :: Python :: 3.8
Classifier: Programming Language :: Python :: 3.9
Classifier: Programming Language :: Python :: 3.10
Classifier: Programming Language :: Python :: 3.11
Classifier: Topic :: Scientific/Engineering :: Physics
Requires-Dist: numpy
Requires-Dist: scipy
Requires-Dist: matplotlib
Requires-Dist: h5py
Requires-Dist: pandas
Requires-Dist: lxml~=4.8
Requires-Dist: more_itertools
Requires-Dist: seaborn
Requires-Dist: deepdiff
Requires-Dist: humanfriendly
Requires-Dist: mendeleev
Requires-Dist: click
Requires-Dist: click-completion
Requires-Dist: PyYAML
Requires-Dist: typing-extensions
Requires-Dist: tabulate
Requires-Dist: ase
Requires-Dist: spglib
Requires-Dist: bokeh ; extra == "bokeh-plots"
Requires-Dist: python-gitlab ; extra == "cmdline-extras"
Requires-Dist: pymatgen-io-fleur~=0.4,>=0.4.1 ; extra == "cmdline-extras"
Requires-Dist: bumpver ; extra == "dev"
Requires-Dist: sphinx~=5.0 ; extra == "docs"
Requires-Dist: sphinx_rtd_theme ; extra == "docs"
Requires-Dist: sphinx-click ; extra == "docs"
Requires-Dist: sphinx-autodoc-typehints!=1.19.3 ; extra == "docs"
Requires-Dist: myst-nb ; extra == "docs"
Requires-Dist: sphinx-copybutton ; extra == "docs"
Requires-Dist: mypy==0.991 ; extra == "pre-commit"
Requires-Dist: pre-commit>=2.6.0 ; extra == "pre-commit"
Requires-Dist: yapf>=0.30.0 ; extra == "pre-commit"
Requires-Dist: pylint~=2.14 ; extra == "pre-commit"
Requires-Dist: pytest~=6.0 ; extra == "pre-commit"
Requires-Dist: lxml-stubs~=0.4.0 ; extra == "pre-commit"
Requires-Dist: types-pytz ; extra == "pre-commit"
Requires-Dist: types-tabulate ; extra == "pre-commit"
Requires-Dist: types-click ; extra == "pre-commit"
Requires-Dist: types-pygments ; extra == "pre-commit"
Requires-Dist: pytest~=6.0 ; extra == "testing"
Requires-Dist: pytest-cov~=3.0 ; extra == "testing"
Requires-Dist: pytest-mpl>=0.12 ; extra == "testing"
Requires-Dist: pytest-regressions>=1.0 ; extra == "testing"
Project-URL: Documentation, https://masci-tools.readthedocs.io
Project-URL: Home, https://masci-tools.readthedocs.io
Project-URL: Source, https://github.com/JuDFTteam/masci-tools
Provides-Extra: bokeh-plots
Provides-Extra: cmdline-extras
Provides-Extra: dev
Provides-Extra: docs
Provides-Extra: pre-commit
Provides-Extra: testing
